text_to_speech_program/__init__.py
text_to_speech_program/client.py
text_to_speech_program/config.py
text_to_speech_program/server.py
text_to_speech_program/work_audio.py
text_to_speech_program/icons/text_to_speech_program.png
text_to_speech_program-0.1.5.dist-info/LICENSE
text_to_speech_program-0.1.5.dist-info/METADATA
text_to_speech_program-0.1.5.dist-info/WHEEL
text_to_speech_program-0.1.5.dist-info/entry_points.txt
text_to_speech_program-0.1.5.dist-info/top_level.txt
text_to_speech_program-0.1.5.dist-info/RECORD
