Metadata-Version: 2.1
Name: text-to-speech-program
Version: 0.1.5
Summary: A text-to-speech server and client using gtts and pydub
Home-page: https://github.com/trucomanx/text_to_speech_program
Author: Fernando Pujaico Rivera
Author-email: fernando.pujaico.rivera@gmail.com
Maintainer: Fernando Pujaico Rivera
Maintainer-email: fernando.pujaico.rivera@gmail.com
License: UNKNOWN
Project-URL: Bug Reports, https://github.com/trucomanx/text_to_speech_program/issues
Project-URL: Funding, https://trucomanx.github.io/en/funding.html
Project-URL: Source, https://github.com/trucomanx/text_to_speech_program/
Keywords: tts,gtts,server
Platform: UNKNOWN
Classifier: Programming Language :: Python :: 3
Classifier: License :: OSI Approved :: GNU General Public License v3 or later (GPLv3+)
Classifier: Operating System :: OS Independent
Requires-Python: >=3.8
License-File: LICENSE
Requires-Dist: Flask
Requires-Dist: gtts
Requires-Dist: pydub
Requires-Dist: requests
